figchain/__init__.py
figchain/auth.py
figchain/client.py
figchain/config.py
figchain/evaluation.py
figchain/models.py
figchain/models_dto.py
figchain/schema.avsc
figchain/serialization.py
figchain/store.py
figchain/transport.py
figchain/util.py
figchain/version.py
figchain/bootstrap/__init__.py
figchain/bootstrap/fallback.py
figchain/bootstrap/hybrid.py
figchain/bootstrap/server.py
figchain/bootstrap/strategy.py
figchain/bootstrap/vault.py
figchain/encryption/crypto.py
figchain/encryption/service.py
figchain/vault/__init__.py
figchain/vault/crypto.py
figchain/vault/fetcher.py
figchain/vault/service.py
figchain-0.2.2.dist-info/licenses/LICENSE
figchain-0.2.2.dist-info/METADATA
figchain-0.2.2.dist-info/WHEEL
figchain-0.2.2.dist-info/top_level.txt
figchain-0.2.2.dist-info/RECORD
