Metadata-Version: 2.4
Name: figchain
Version: 0.2.2
Summary: FigChain Python Client
Author-email: FigChain Team <support@figchain.io>
License: 
Keywords: figchain,configuration,feature-flags
Classifier: Programming Language :: Python :: 3
Classifier: License :: OSI Approved :: Apache Software License
Classifier: Operating System :: OS Independent
Requires-Python: >=3.7
License-File: LICENSE
Requires-Dist: requests>=2.25.0
Requires-Dist: avro>=1.11.0
Requires-Dist: typing-extensions>=4.0.0
Requires-Dist: boto3>=1.20.0
Requires-Dist: cryptography>=3.0.0
Requires-Dist: pyjwt>=2.0.0
Requires-Dist: pyyaml>=6.0
Provides-Extra: dev
Requires-Dist: pytest; extra == "dev"
Requires-Dist: pylint; extra == "dev"
Requires-Dist: mypy; extra == "dev"
Requires-Dist: black; extra == "dev"
Requires-Dist: avro-gen3; extra == "dev"
Dynamic: license-file
